adafruit_circuitpython_itertools-2.1.6.dist-info/licenses/LICENSE
adafruit_itertools/__init__.py
adafruit_itertools/adafruit_itertools_extras.py
adafruit_circuitpython_itertools-2.1.6.dist-info/METADATA
adafruit_circuitpython_itertools-2.1.6.dist-info/WHEEL
adafruit_circuitpython_itertools-2.1.6.dist-info/top_level.txt
adafruit_circuitpython_itertools-2.1.6.dist-info/RECORD
